repomd.py
repomd-0.2.1.dist-info/LICENSE
repomd-0.2.1.dist-info/METADATA
repomd-0.2.1.dist-info/WHEEL
repomd-0.2.1.dist-info/top_level.txt
repomd-0.2.1.dist-info/RECORD
