Metadata-Version: 2.1
Name: repomd
Version: 0.2.1
Summary: Library for reading dnf/yum repositories
Home-page: https://github.com/carlwgeorge/repomd
Author: Carl George
Author-email: carl@george.computer
License: MIT
Platform: UNKNOWN
Classifier: License :: OSI Approved :: MIT License
Classifier: Operating System :: OS Independent
Classifier: Programming Language :: Python :: 3 :: Only
Requires-Python: >=3.6
Requires-Dist: defusedxml
Requires-Dist: lxml
Provides-Extra: test
Requires-Dist: pytest ; extra == 'test'
Requires-Dist: pytest-cov ; extra == 'test'
Requires-Dist: pytest-flake8 ; extra == 'test'
